discord/ext/interaction/__init__.py
discord/ext/interaction/_types.py
discord/ext/interaction/checks.py
discord/ext/interaction/client.py
discord/ext/interaction/commands.py
discord/ext/interaction/components.py
discord/ext/interaction/core.py
discord/ext/interaction/enums.py
discord/ext/interaction/errors.py
discord/ext/interaction/http.py
discord/ext/interaction/interaction.py
discord/ext/interaction/listener.py
discord/ext/interaction/message.py
discord/ext/interaction/utils.py
Discord_Extension_Interaction-0.6.2.dist-info/LICENSE
Discord_Extension_Interaction-0.6.2.dist-info/METADATA
Discord_Extension_Interaction-0.6.2.dist-info/WHEEL
Discord_Extension_Interaction-0.6.2.dist-info/top_level.txt
Discord_Extension_Interaction-0.6.2.dist-info/RECORD
