Metadata-Version: 2.1
Name: Discord-Extension-Interaction
Version: 0.6.2
Summary: Framework for Application Commands built on discord.py
Home-page: https://github.com/gunyu1019/discord-extension-interaction
Author: gunyu1019
Author-email: gunyu1019@yhs.kr
License: MIT
Classifier: Development Status :: 4 - Beta
Classifier: License :: OSI Approved :: MIT License
Classifier: Intended Audience :: Developers
Classifier: Natural Language :: Korean
Classifier: Natural Language :: English
Classifier: Programming Language :: Python
Classifier: Programming Language :: Python :: 3.10
Classifier: Programming Language :: Python :: 3.11
Classifier: Topic :: Internet
Classifier: Topic :: Software Development :: Libraries
Classifier: Topic :: Software Development :: Libraries :: Python Modules
Classifier: Topic :: Utilities
Requires-Python: >=3.10
License-File: LICENSE
Requires-Dist: aiohttp >=3.9.3
Requires-Dist: aiosignal >=1.3.1
Requires-Dist: async-timeout >=4.0.3
Requires-Dist: asyncio >=3.4.3
Requires-Dist: attrs >=23.2.0
Requires-Dist: frozenlist >=1.4.1
Requires-Dist: idna >=3.6
Requires-Dist: multidict >=6.0.5
Requires-Dist: yarl >=1.9.4
Provides-Extra: discordpy
Requires-Dist: discord.py ; extra == 'discordpy'
Provides-Extra: lint
Requires-Dist: pycodestyle ; extra == 'lint'
Requires-Dist: black ; extra == 'lint'
Provides-Extra: pycord
Requires-Dist: py-cord ; extra == 'pycord'
Provides-Extra: test
Requires-Dist: pytest ; extra == 'test'
Requires-Dist: pytest-cov ; extra == 'test'
